amiadmin/LICENSE
amiadmin/README.MD
amiadmin/__init__.py
amiadmin/requirements.txt
amiadmin/thirdparty.json
amiadmin-0.10.dist-info/LICENSE.rst
amiadmin-0.10.dist-info/METADATA
amiadmin-0.10.dist-info/WHEEL
amiadmin-0.10.dist-info/top_level.txt
amiadmin-0.10.dist-info/RECORD
